pysunsynkweb/__about__.py
pysunsynkweb/__init__.py
pysunsynkweb/battery.py
pysunsynkweb/const.py
pysunsynkweb/exceptions.py
pysunsynkweb/inverter.py
pysunsynkweb/model.py
pysunsynkweb/pvstring.py
pysunsynkweb/session.py
pysunsynkweb-0.0.7.dist-info/METADATA
pysunsynkweb-0.0.7.dist-info/WHEEL
pysunsynkweb-0.0.7.dist-info/licenses/LICENSE.txt
pysunsynkweb-0.0.7.dist-info/RECORD
